orb/__init__.py
orb/_base_client.py
orb/_client.py
orb/_compat.py
orb/_constants.py
orb/_exceptions.py
orb/_files.py
orb/_legacy_response.py
orb/_models.py
orb/_qs.py
orb/_resource.py
orb/_response.py
orb/_streaming.py
orb/_types.py
orb/_version.py
orb/pagination.py
orb/py.typed
orb/_utils/__init__.py
orb/_utils/_compat.py
orb/_utils/_datetime_parse.py
orb/_utils/_json.py
orb/_utils/_logs.py
orb/_utils/_proxy.py
orb/_utils/_reflection.py
orb/_utils/_resources_proxy.py
orb/_utils/_streams.py
orb/_utils/_sync.py
orb/_utils/_transform.py
orb/_utils/_typing.py
orb/_utils/_utils.py
orb/lib/.keep
orb/resources/__init__.py
orb/resources/alerts.py
orb/resources/credit_blocks.py
orb/resources/credit_notes.py
orb/resources/invoice_line_items.py
orb/resources/invoices.py
orb/resources/items.py
orb/resources/metrics.py
orb/resources/subscription_changes.py
orb/resources/subscriptions.py
orb/resources/top_level.py
orb/resources/webhooks.py
orb/resources/beta/__init__.py
orb/resources/beta/beta.py
orb/resources/beta/external_plan_id.py
orb/resources/coupons/__init__.py
orb/resources/coupons/coupons.py
orb/resources/coupons/subscriptions.py
orb/resources/customers/__init__.py
orb/resources/customers/balance_transactions.py
orb/resources/customers/costs.py
orb/resources/customers/customers.py
orb/resources/customers/credits/__init__.py
orb/resources/customers/credits/credits.py
orb/resources/customers/credits/ledger.py
orb/resources/customers/credits/top_ups.py
orb/resources/dimensional_price_groups/__init__.py
orb/resources/dimensional_price_groups/dimensional_price_groups.py
orb/resources/dimensional_price_groups/external_dimensional_price_group_id.py
orb/resources/events/__init__.py
orb/resources/events/backfills.py
orb/resources/events/events.py
orb/resources/events/volume.py
orb/resources/plans/__init__.py
orb/resources/plans/external_plan_id.py
orb/resources/plans/migrations.py
orb/resources/plans/plans.py
orb/resources/prices/__init__.py
orb_billing-4.51.0.dist-info/METADATA
orb_billing-4.51.0.dist-info/WHEEL
orb_billing-4.51.0.dist-info/licenses/LICENSE
orb_billing-4.51.0.dist-info/RECORD
